Metadata-Version: 2.1
Name: rtmlib_pose2sim
Version: 0.0.13
Summary: A library for real-time pose estimation.
Home-page: https://github.com/davidpagnon/rtmlib_Pose2Sim
Author: Tau-J, David Pagnon
Author-email: taujiang@outlook.com, contact@david-pagnon.com
License: Apache License 2.0
Keywords: pose estimation
Requires-Python: >=3.7
License-File: LICENSE
Provides-Extra: all
Requires-Dist: numpy; extra == "all"
Requires-Dist: onnxruntime; extra == "all"
Requires-Dist: opencv-contrib-python; extra == "all"
Requires-Dist: opencv-python; extra == "all"
Requires-Dist: tqdm; extra == "all"
Provides-Extra: optional
